cyMStools/__init__.py
cyMStools/cal_similarity_of2spec.py
cyMStools/plink2_summary.py
cyMStools-0.0.6.1.dist-info/LICENSE
cyMStools-0.0.6.1.dist-info/METADATA
cyMStools-0.0.6.1.dist-info/WHEEL
cyMStools-0.0.6.1.dist-info/top_level.txt
cyMStools-0.0.6.1.dist-info/RECORD
