Metadata-Version: 2.1
Name: cyMStools
Version: 0.0.6.1
Summary: mass spec tools
Home-page: https://github.com/daheitu/cyMStools
Author: zhyCAO
Author-email: zhycao@outlook.com
License: UNKNOWN
Platform: UNKNOWN
Classifier: Programming Language :: Python :: 3
Classifier: License :: OSI Approved :: MIT License
Classifier: Operating System :: OS Independent
